Workbook

Sheet Ratios
A1: Company | B1: Costco | C1: Walmart | D1: Costco | E1: Walmart
A2: Fiscal year | B2: 2025 | C2: 2025 | D2: 2025 | E2: 2025
A3: Scale | B3: (millions) | C3: (millions) | D3: (billions) | E3: (billions)
A4: Income statement values
A5: Total revenue | B5: ='Costco income statement'!B4 -> 275235 | C5: ='Walmart income statement'!B6 -> 680985 | D5: =ROUND(B5/1000,1) -> 275.2 | E5: =ROUND(C5/1000,1) -> 681
A6: COGS | B6: ='Costco income statement'!B5 -> 239886 | C6: ='Walmart income statement'!B7 -> 511753 | D6: =ROUND(B6/1000,1) -> 239.9 | E6: =ROUND(C6/1000,1) -> 511.8
A7: SG&A | B7: ='Costco income statement'!B6 -> 24966 | C7: ='Walmart income statement'!B8 -> 139884 | D7: =ROUND(B7/1000,1) -> 25 | E7: =ROUND(C7/1000,1) -> 139.9
A8: NOPAT | B8: ='Costco income statement'!B7*(1-'Costco income statement'!B14) -> 7773.3331 | C8: ='Walmart income statement'!B9*(1-'Walmart income statement'!B19) -> 22485.371 | D8: =ROUND(B8/1000,1) -> 7.8 | E8: =ROUND(C8/1000,1) -> 22.5
A9: Balance sheet values (average)
A10: Current assets | B10: ='Costco balance sheet'!D9 -> 36313 | C10: ='Walmart balance sheet'!D8 -> 78167.5 | D10: =ROUND(B10/1000,1) -> 36.3 | E10: =ROUND(C10/1000,1) -> 78.2
A11: Net PPE + leases | B11: =SUM('Costco balance sheet'!D10:D11) -> 33141.5 | C11: =SUM('Walmart balance sheet'!D9:D11) -> 135021 | D11: =ROUND(B11/1000,1) -> 33.1 | E11: =ROUND(C11/1000,1) -> 135
A12: Other long-term assets | B12: ='Costco balance sheet'!D12 -> 4010.5 | C12: =SUM('Walmart balance sheet'!D12:D13) -> 43422.5 | D12: =ROUND(B12/1000,1) -> 4 | E12: =ROUND(C12/1000,1) -> 43.4
A13: NIBCLs | B13: =SUM('Costco balance sheet'!D14:D18) -> 36286 | C13: =SUM('Walmart balance sheet'!D16:D18) -> 87248.5 | D13: =ROUND(B13/1000,1) -> 36.3 | E13: =ROUND(C13/1000,1) -> 87.2
A14: Excess cash | B14: ='Costco balance sheet'!D26 -> 2620.24 | C14: ='Walmart balance sheet'!D31 -> 0 | D14: =ROUND(B14/1000,1) -> 2.6 | E14: =ROUND(C14/1000,1) -> 0
A15: Net working capital | B15: =B10-B13-B14 -> -2593.24 | C15: =C10-C13-C14 -> -9081 | D15: =ROUND(B15/1000,1) -> -2.6 | E15: =ROUND(C15/1000,1) -> -9.1
A16: Invested capital | B16: =B15+B11+B12 -> 34558.76 | C16: =C15+C11+C12 -> 169362.5 | D16: =ROUND(B16/1000,1) -> 34.6 | E16: =ROUND(C16/1000,1) -> 169.4
A17: Store square feet | B17: ='Costco balance sheet'!D27 -> 132.8 | C17: ='Walmart balance sheet'!D32 -> 1014.45 | D17: =B17/1000 -> 0.1328 | E17: =C17/1000 -> 1.01445
A18: Ratios
A19: ROIC | D19: =D8/D16 -> 0.22543353 | E19: =E8/E16 -> 0.13282172
A20: Return on sales | D20: =D8/D5 -> 0.028343023 | E20: =E8/E5 -> 0.033039648
A21: COGS / sales | D21: =D6/D5 -> 0.87172965 | E21: =E6/E5 -> 0.75154185
A22: SG&A / sales | D22: =D7/D5 -> 0.090843023 | E22: =E7/E5 -> 0.20543319
A23: Capital turnover | D23: =D5/D16 -> 7.9537572 | E23: =E5/E16 -> 4.0200708
A24: Avg. NWC / sales | D24: =D15/D5 -> -0.0094476744 | E24: =E15/E5 -> -0.013362702
A25: Avg. PPE / sales | D25: =D11/D5 -> 0.12027616 | E25: =E11/E5 -> 0.19823789
A26: Revenue / square foot | D26: =D5/D17 -> 2072.2892 | E26: =E5/E17 -> 671.29972

Sheet Costco income statement
B2: For the year ending
A3: Income statement (in millions) | B3: 45900 | C3: 45536
A4: Total revenues | B4: 275235 | C4: 254453
A5: Merchandise costs | B5: 239886 | C5: 222358
A6: SG&A expenses | B6: 24966 | C6: 22810
A7: Operating income | B7: 10383 | C7: 9285
A8: Interest expense | B8: -154 | C8: -169
A9: Interest income and other, net | B9: 589 | C9: 624
A10: Income before income taxes | B10: 10818 | C10: 9470
A11: Provision for income taxes | B11: 2719 | C11: 2373
A12: Net income | B12: 8099 | C12: 7367
A13: Other data
A14: Effective tax rate | B14: =B11/B10 -> 0.25134036 | C14: =C11/C10 -> 0.25058078
A16: Source: Costco FY2025 10-K

Sheet Costco balance sheet
B2: Year ending
A3: Balance sheet (in millions) | B3: 45688 | C3: 45322 | D3: Average
A4: Cash and cash equivalents | B4: 14161 | C4: 9906 | D4: =AVERAGE(B4:C4) -> 12033.5
A5: Short-term investments | B5: 1123 | C5: 1238 | D5: =AVERAGE(B5:C5) -> 1180.5
A6: Receivables, net | B6: 3203 | C6: 2721 | D6: =AVERAGE(B6:C6) -> 2962
A7: Merchandise inventories | B7: 18116 | C7: 18647 | D7: =AVERAGE(B7:C7) -> 18381.5
A8: Other current assets | B8: 1777 | C8: 1734 | D8: =AVERAGE(B8:C8) -> 1755.5
A9: Total current assets | B9: 38380 | C9: 34246 | D9: =AVERAGE(B9:C9) -> 36313
A10: Property and equipment, net | B10: 31909 | C10: 29032 | D10: =AVERAGE(B10:C10) -> 30470.5
A11: Operating lease right-of-use assets | B11: 2725 | C11: 2617 | D11: =AVERAGE(B11:C11) -> 2671
A12: Other long-term assets | B12: 4085 | C12: 3936 | D12: =AVERAGE(B12:C12) -> 4010.5
A13: Total assets | B13: 77099 | C13: 69831 | D13: =AVERAGE(B13:C13) -> 73465
A14: Accounts payable | B14: 19783 | C14: 19421 | D14: =AVERAGE(B14:C14) -> 19602
A15: Accrued salaries and benefits | B15: 5205 | C15: 4794 | D15: =AVERAGE(B15:C15) -> 4999.5
... A24: Total liabilities & shareholders' equity | B24: 77099 | C24: 69831 | D24: =AVERAGE(B24:C24) -> 73465
A25: Other items (in millions)
A26: Excess cash | B26: =MAX(0,SUM(B4:B5)-'Costco income statement'!B4*0.04) -> 4274.6 | C26: =MAX(0,SUM(C4:C5)-'Costco income statement'!C4*0.04) -> 965.88 | D26: =AVERAGE(B26:C26) -> 2620.24
A27: Store square feet | B27: 134.7 | C27: 130.9 | D27: =AVERAGE(B27:C27) -> 132.8
A29: Source: Costco FY2025 10-K

Sheet Walmart income statement
B2: For the year ending
A3: Income statement (in millions) | B3: 45688 | C3: 45322
A4: Net sales | B4: 674538 | C4: 642637
A5: Membership and other income | B5: 6447 | C5: 5488
A6: Total revenues | B6: 680985 | C6: 648125
A7: Cost of sales | B7: 511753 | C7: 490142
A8: SG&A expenses | B8: 139884 | C8: 130971
A9: Operating income | B9: 29348 | C9: 27012
A10: Debt | B10: 2249 | C10: 2259
A11: Finance lease | B11: 479 | C11: 424
A12: Interest income | B12: -483 | C12: -546
A13: Interest, net | B13: 2245 | C13: 2137
A14: Other (gains) and losses | B14: 794 | C14: 3027
... A17: Net income | B17: 20157 | C17: 16270
A18: Other data
A19: Effective tax rate | B19: =B16/B15 -> 0.23383633 | C19: =C16/C15 -> 0.25530941
A21: Source: Walmart FY2025 10-K

Sheet Walmart balance sheet
B2: Year ending
A3: Balance sheet (in millions) | B3: 45688 | C3: 45322 | D3: Average
A4: Cash and cash equivalents | B4: 9037 | C4: 9867 | D4: =AVERAGE(B4:C4) -> 9452
A5: Receivables, net | B5: 9975 | C5: 8796 | D5: =AVERAGE(B5:C5) -> 9385.5
A6: Inventories | B6: 56435 | C6: 54892 | D6: =AVERAGE(B6:C6) -> 55663.5
A7: Prepaid expenses and other | B7: 4011 | C7: 3322 | D7: =AVERAGE(B7:C7) -> 3666.5
A8: Total current assets | B8: 79458 | C8: 76877 | D8: =AVERAGE(B8:C8) -> 78167.5
A9: Property and equipment, net | B9: 119993 | C9: 110810 | D9: =AVERAGE(B9:C9) -> 115401.5
A10: Operating lease right-of-use assets | B10: 13599 | C10: 13673 | D10: =AVERAGE(B10:C10) -> 13636
A11: Finance lease right-of-use assets, net | B11: 6112 | C11: 5855 | D11: =AVERAGE(B11:C11) -> 5983.5
A12: Goodwill | B12: 28792 | C12: 28113 | D12: =AVERAGE(B12:C12) -> 28452.5
A13: Other long-term assets | B13: 12869 | C13: 17071 | D13: =AVERAGE(B13:C13) -> 14970
A14: Total assets | B14: 260823 | C14: 252399 | D14: =AVERAGE(B14:C14) -> 256611
A15: Short-term borrowings | B15: 3068 | C15: 878 | D15: =AVERAGE(B15:C15) -> 1973
... A29: Total liabilities & shareholders' equity | B29: 260823 | C29: 252399 | D29: =AVERAGE(B29:C29) -> 256611
A30: Other items (in millions)
A31: Excess cash | B31: =MAX(0,B4-'Walmart income statement'!B6*0.04) -> 0 | C31: =MAX(0,C4-'Walmart income statement'!C6*0.04) -> 0 | D31: =AVERAGE(B31:C31) -> 0
A32: Store square feet | B32: 1013.6 | C32: 1015.3 | D32: =AVERAGE(B32:C32) -> 1014.45
A34: Source: Walmart FY2025 10-K
